#include "ljit_analyze.h"
#include "../../../core/lopcodes.h"

void ljit_translate(ljit_ctx_t *ctx) {
    if (!ctx || !ctx->proto) return;

    Proto *proto = ctx->proto;

    // Iterate over the bytecode to map high-frequency opcodes to IR
    for (int pc = 0; pc < proto->sizecode; pc++) {
        Instruction i = proto->code[pc];
        OpCode op = GET_OPCODE(i);

        switch (op) {
            case OP_MOVE:
            case OP_LOADI:
            case OP_LOADF:
            case OP_LOADK:
            case OP_LOADKX:
            case OP_LOADFALSE:
            case OP_LFALSESKIP:
            case OP_LOADTRUE:
            case OP_LOADNIL:
            case OP_GETUPVAL:
            case OP_SETUPVAL:
            case OP_GETTABUP:
            case OP_GETTABLE:
            case OP_GETI:
            case OP_GETFIELD:
            case OP_SETTABUP:
            case OP_SETTABLE:
            case OP_SETI:
            case OP_SETFIELD:
            case OP_NEWTABLE:
            case OP_SELF:
            case OP_ADDI:
            case OP_ADDK:
            case OP_SUBK:
            case OP_MULK:
            case OP_MODK:
            case OP_POWK:
            case OP_DIVK:
            case OP_IDIVK:
            case OP_BANDK:
            case OP_BORK:
            case OP_BXORK:
            case OP_SHRI:
            case OP_SHLI:
            case OP_ADD:
            case OP_SUB:
            case OP_MUL:
            case OP_MOD:
            case OP_POW:
            case OP_DIV:
            case OP_IDIV:
            case OP_BAND:
            case OP_BOR:
            case OP_BXOR:
            case OP_SHL:
            case OP_SHR:
            case OP_MMBIN:
            case OP_MMBINI:
            case OP_MMBINK:
            case OP_UNM:
            case OP_BNOT:
            case OP_NOT:
            case OP_LEN:
            case OP_CONCAT:
            case OP_CLOSE:
            case OP_TBC:
            case OP_JMP:
            case OP_EQ:
            case OP_LT:
            case OP_LE:
            case OP_EQK:
            case OP_EQI:
            case OP_LTI:
            case OP_LEI:
            case OP_GTI:
            case OP_GEI:
            case OP_TEST:
            case OP_TESTSET:
            case OP_CALL:
            case OP_TAILCALL:
            case OP_RETURN:
            case OP_RETURN0:
            case OP_RETURN1:
            case OP_FORLOOP:
            case OP_FORPREP:
            case OP_TFORCALL:
            case OP_TFORPREP:
            case OP_TFORLOOP:
            case OP_SETLIST:
            case OP_CLOSURE:
            case OP_VARARG:
            case OP_VARARGPREP:
            case OP_EXTRAARG:
            case OP_NEWCLASS:
            case OP_NEWOBJ:
            case OP_NEWNAMESPACE:
            case OP_NEWCONCEPT:
            case OP_LINKNAMESPACE:
            case OP_IMPLEMENT:
            case OP_INHERIT:
            case OP_SETMETHOD:
            case OP_SETSTATIC:
            case OP_ADDMETHOD:
            case OP_SETIFACEFLAG:
            case OP_SETPROP:
            case OP_GETPROP:
            case OP_GETCMDS:
            case OP_GETOPS:
            case OP_GETSUPER:
            case OP_NEWSUPER:
            case OP_SETSUPER:
            case OP_INSTANCEOF:
            case OP_IS:
            case OP_IN:
            case OP_CASE:
            case OP_CHECKTYPE:
            case OP_SLICE:
            case OP_SPACESHIP:
            case OP_GETVARG:
            case OP_ASYNCWRAP:
            case OP_GENERICWRAP:
            case OP_ERRNNIL:
            case OP_NOP:
                // Translate all opcodes
                // Placeholder logic updated to use new IR API
                {
                    ljit_ir_node_t *node = ljit_ir_new(IR_NOP, pc);
                    ljit_ir_append(ctx, node);
                }
                break;
            default:
                // Handle unknown opcodes
                break;
        }
    }
}
